<?xml version="1.0" encoding="UTF-8"?>
<build-type xmlns:xsi="http://www.w3.org/2001/XMLSchema-instance" uuid="3ed33d67-f980-4084-a1b6-889b3775ce60" xsi:noNamespaceSchemaLocation="http://www.jetbrains.com/teamcity/schemas/9.0/project-config.xsd">
  <name>Build, Test, Sonar, NuGET Pack, Publish</name>
  <description />
  <settings>
    <parameters />
    <build-runners />
    <vcs-settings>
      <vcs-entry-ref root-id="MarsLifeDevelopment" />
    </vcs-settings>
    <requirements />
    <build-triggers />
    <cleanup />
  </settings>
</build-type>

